appium/__init__.py
appium/swipe/__init__.py
appium/swipe/actions.py
appium_swipe_actions-0.1.3.dist-info/METADATA
appium_swipe_actions-0.1.3.dist-info/WHEEL
appium_swipe_actions-0.1.3.dist-info/licenses/LICENSE
appium_swipe_actions-0.1.3.dist-info/RECORD
