Metadata-Version: 2.3
Name: appium-swipe-actions
Version: 0.1.3
Summary: Enhanced Swipe Actions Library for Appium
Project-URL: homepage, https://github.com/Tanakrit-D/Appium-Swipe-Actions
Project-URL: repository, https://github.com/Tanakrit-D/Appium-Swipe-Actions
Project-URL: issues, https://github.com/Tanakrit-D/Appium-Swipe-Actions/issues
Author-email: Dominic <127579510+Tanakrit-D@users.noreply.github.com>
License: MIT License
License-File: LICENSE
Keywords: appium,scroll,swipe
Classifier: License :: OSI Approved :: MIT License
Classifier: Operating System :: OS Independent
Classifier: Programming Language :: Python :: 3
Requires-Python: >=3.8
Requires-Dist: appium-python-client>=4.1.0
Requires-Dist: selenium>=4.24.0
